README.rst
setup.py
injectables/__init__.py
injectables/decorators.py
injectables.egg-info/PKG-INFO
injectables.egg-info/SOURCES.txt
injectables.egg-info/dependency_links.txt
injectables.egg-info/top_level.txt