Metadata-Version: 1.1
Name: injectables
Version: 0.0.6
Summary: A super lightweight python injection library. It does one thing, it creates injectables.
Home-page: https://github.com/mattrwh/injectables
Author: Matthew Whitt
Author-email: mwhitt.w@gmail.com
License: MIT
Keywords: dependency injection
Platform: UNKNOWN
Classifier: Development Status :: 3 - Alpha
Classifier: Intended Audience :: Developers
Classifier: License :: OSI Approved :: MIT License
Classifier: Programming Language :: Python :: 3
Classifier: Programming Language :: Python :: 3.3
Classifier: Programming Language :: Python :: 3.4
Classifier: Programming Language :: Python :: 3.5
